aiodns/__init__.py
aiodns/error.py
aiodns-3.1.1.dist-info/LICENSE
aiodns-3.1.1.dist-info/METADATA
aiodns-3.1.1.dist-info/WHEEL
aiodns-3.1.1.dist-info/top_level.txt
aiodns-3.1.1.dist-info/RECORD
