Metadata-Version: 2.1
Name: aiodns
Version: 3.1.1
Summary: Simple DNS resolver for asyncio
Home-page: https://github.com/saghul/aiodns
Author: Saúl Ibarra Corretgé
Author-email: s@saghul.net
License: MIT
Platform: POSIX
Platform: Microsoft Windows
Classifier: Development Status :: 5 - Production/Stable
Classifier: Intended Audience :: Developers
Classifier: License :: OSI Approved :: MIT License
Classifier: Operating System :: POSIX
Classifier: Operating System :: Microsoft :: Windows
Classifier: Programming Language :: Python
Classifier: Programming Language :: Python :: 3
Classifier: Programming Language :: Python :: 3.8
Classifier: Programming Language :: Python :: 3.9
Classifier: Programming Language :: Python :: 3.10
Classifier: Programming Language :: Python :: 3.11
Classifier: Programming Language :: Python :: 3.12
